{
	"format_version": "1.21.11",
	"credit": "Made with Blockbench",
	"texture_size": [32, 32],
	"textures": {
		"0": "finalpeak:item/animated_propeller_hat",
		"particle": "finalpeak:item/animated_propeller_hat"
	},
	"elements": [
		{
			"from": [4.001, 6.15697, 1.43118],
			"to": [11.999, 7.15697, 6.43118],
			"rotation": {"angle": -2.5, "axis": "x", "origin": [8, 7.05, 7]},
			"faces": {
				"north": {"uv": [5.5, 8, 9.5, 8.5], "texture": "#0"},
				"east": {"uv": [8, 6.5, 10.5, 7], "texture": "#0"},
				"south": {"uv": [8, 6, 12, 6.5], "texture": "#0"},
				"west": {"uv": [8, 7, 10.5, 7.5], "texture": "#0"},
				"up": {"uv": [8, 2.5, 4, 0], "texture": "#0"},
				"down": {"uv": [8, 2.5, 4, 5], "texture": "#0"}
			}
		},
		{
			"from": [4, 6, 4],
			"to": [12, 9, 12],
			"rotation": {"angle": 5, "axis": "x", "origin": [8, 7, 8]},
			"faces": {
				"north": {"uv": [4, 5, 8, 6.5], "texture": "#0"},
				"east": {"uv": [4, 6.5, 8, 8], "texture": "#0"},
				"south": {"uv": [0, 8, 4, 9.5], "texture": "#0"},
				"west": {"uv": [8, 0, 12, 1.5], "texture": "#0"},
				"up": {"uv": [4, 4, 0, 0], "texture": "#0"},
				"down": {"uv": [4, 4, 0, 8], "texture": "#0"}
			}
		},
		{
			"from": [7.5, 9, 7.5],
			"to": [8.5, 10, 8.5],
			"rotation": {"angle": 5, "axis": "x", "origin": [8.5, 7, 8.5]},
			"faces": {
				"north": {"uv": [8, 7.5, 8.5, 8], "texture": "#0"},
				"east": {"uv": [8.5, 1.5, 9, 2], "texture": "#0"},
				"south": {"uv": [8.5, 2, 9, 2.5], "texture": "#0"},
				"west": {"uv": [8.5, 2.5, 9, 3], "texture": "#0"},
				"up": {"uv": [9, 3.5, 8.5, 3], "texture": "#0"},
				"down": {"uv": [9, 3.5, 8.5, 4], "texture": "#0"}
			}
		},
		{
			"from": [7.5, 10.08216, 3.76337],
			"to": [8.5, 10.08216, 12.76337],
			"rotation": {"x": 6.80703, "y": 44.74264, "z": 6.10019, "origin": [8, 10.08216, 8.26337]},
			"faces": {
				"north": {"uv": [0, 0, 0.5, 0], "texture": "#0"},
				"east": {"uv": [0, 0, 4.5, 0], "texture": "#0"},
				"south": {"uv": [0, 0, 0.5, 0], "texture": "#0"},
				"west": {"uv": [0, 0, 4.5, 0], "texture": "#0"},
				"up": {"uv": [0.5, 14, 0, 9.5], "texture": "#0"},
				"down": {"uv": [0.5, 9.5, 0, 14], "texture": "#0"}
			}
		},
		{
			"from": [7.5, 10.05716, 3.76337],
			"to": [8.5, 10.05716, 12.76337],
			"rotation": {"x": 173.18009, "y": 44.85128, "z": 176.47586, "origin": [8, 10.05716, 8.26337]},
			"faces": {
				"north": {"uv": [0, 0, 0.5, 0], "texture": "#0"},
				"east": {"uv": [0, 0, 4.5, 0], "texture": "#0"},
				"south": {"uv": [0, 0, 0.5, 0], "texture": "#0"},
				"west": {"uv": [0, 0, 4.5, 0], "texture": "#0"},
				"up": {"uv": [0.5, 14, 0, 9.5], "texture": "#0"},
				"down": {"uv": [0.5, 9.5, 0, 14], "texture": "#0"}
			}
		},
		{
			"from": [7.5, 10.05716, 3.76337],
			"to": [8.5, 10.05716, 12.76337],
			"rotation": {"x": 174.63784, "y": 22.38306, "z": 177.29873, "origin": [8, 10.05716, 8.26337]},
			"faces": {
				"north": {"uv": [0, 0, 0.5, 0], "texture": "#0"},
				"east": {"uv": [0, 0, 4.5, 0], "texture": "#0"},
				"south": {"uv": [0, 0, 0.5, 0], "texture": "#0"},
				"west": {"uv": [0, 0, 4.5, 0], "texture": "#0"},
				"up": {"uv": [1, 14, 0.5, 9.5], "texture": "#0"},
				"down": {"uv": [1, 9.5, 0.5, 14], "texture": "#0"}
			}
		},
		{
			"from": [7.5, 10.08216, 3.76337],
			"to": [8.5, 10.08216, 12.76337],
			"rotation": {"x": 12.785, "y": 67.01575, "z": 11.14538, "origin": [8, 10.08216, 8.26337]},
			"faces": {
				"north": {"uv": [0, 0, 0.5, 0], "texture": "#0"},
				"east": {"uv": [0, 0, 4.5, 0], "texture": "#0"},
				"south": {"uv": [0, 0, 0.5, 0], "texture": "#0"},
				"west": {"uv": [0, 0, 4.5, 0], "texture": "#0"},
				"up": {"uv": [1, 14, 0.5, 9.5], "texture": "#0"},
				"down": {"uv": [1, 9.5, 0.5, 14], "texture": "#0"}
			}
		},
		{
			"from": [7.5, 10.05716, 3.76337],
			"to": [8.5, 10.05716, 12.76337],
			"rotation": {"x": 175.67125, "y": -0.09441, "z": 177.50238, "origin": [8, 10.05716, 8.26337]},
			"faces": {
				"north": {"uv": [0, 0, 0.5, 0], "texture": "#0"},
				"east": {"uv": [0, 0, 4.5, 0], "texture": "#0"},
				"south": {"uv": [0, 0, 0.5, 0], "texture": "#0"},
				"west": {"uv": [0, 0, 4.5, 0], "texture": "#0"},
				"up": {"uv": [1.5, 14, 1, 9.5], "texture": "#0"},
				"down": {"uv": [1.5, 9.5, 1, 14], "texture": "#0"}
			}
		},
		{
			"from": [7.5, 10.08216, 3.76337],
			"to": [8.5, 10.08216, 12.76337],
			"rotation": {"x": 91.25055, "y": 85.67022, "z": 88.74936, "origin": [8, 10.08216, 8.26337]},
			"faces": {
				"north": {"uv": [0, 0, 0.5, 0], "texture": "#0"},
				"east": {"uv": [0, 0, 4.5, 0], "texture": "#0"},
				"south": {"uv": [0, 0, 0.5, 0], "texture": "#0"},
				"west": {"uv": [0, 0, 4.5, 0], "texture": "#0"},
				"up": {"uv": [1.5, 14, 1, 9.5], "texture": "#0"},
				"down": {"uv": [1.5, 9.5, 1, 14], "texture": "#0"}
			}
		},
		{
			"from": [7.5, 10.05716, 3.76337],
			"to": [8.5, 10.05716, 12.76337],
			"rotation": {"x": 176.70606, "y": -22.57185, "z": 177.29504, "origin": [8, 10.05716, 8.26337]},
			"faces": {
				"north": {"uv": [0, 0, 0.5, 0], "texture": "#0"},
				"east": {"uv": [0, 0, 4.5, 0], "texture": "#0"},
				"south": {"uv": [0, 0, 0.5, 0], "texture": "#0"},
				"west": {"uv": [0, 0, 4.5, 0], "texture": "#0"},
				"up": {"uv": [2, 14, 1.5, 9.5], "texture": "#0"},
				"down": {"uv": [2, 9.5, 1.5, 14], "texture": "#0"}
			}
		},
		{
			"from": [7.5, 10.08216, 3.76337],
			"to": [8.5, 10.08216, 12.76337],
			"rotation": {"x": 172.13008, "y": 67.20151, "z": 168.76759, "origin": [8, 10.08216, 8.26337]},
			"faces": {
				"north": {"uv": [0, 0, 0.5, 0], "texture": "#0"},
				"east": {"uv": [0, 0, 4.5, 0], "texture": "#0"},
				"south": {"uv": [0, 0, 0.5, 0], "texture": "#0"},
				"west": {"uv": [0, 0, 4.5, 0], "texture": "#0"},
				"up": {"uv": [2, 14, 1.5, 9.5], "texture": "#0"},
				"down": {"uv": [2, 9.5, 1.5, 14], "texture": "#0"}
			}
		}
	],
	"display": {
		"head": {
			"translation": [0, 6.5, 0],
			"scale": [2, 2, 2]
		}
	},
	"groups": [
		0,
		1,
		2,
		{
			"name": "group",
			"origin": [8, 10.08216, 8.26337],
			"color": 0,
			"children": [3, 4]
		},
		{
			"name": "group",
			"origin": [8, 10.05716, 8.26337],
			"color": 0,
			"children": [5, 6]
		},
		{
			"name": "group",
			"origin": [8, 10.05716, 8.26337],
			"color": 0,
			"children": [7, 8]
		},
		{
			"name": "group",
			"origin": [8, 10.05716, 8.26337],
			"color": 0,
			"children": [9, 10]
		}
	]
}